{"8": ["rabbit", "coop", "animal"], "9": ["rabbit", "coop", "animal"], "14": ["rabbit", "coop", "animal"], "15": ["rabbit", "coop", "animal"], "17": ["rabbit", "coop", "animal"], "16": ["rabbit", "coop", "animal"], "12": ["rabbit", "coop", "animal"], "13": ["rabbit", "coop", "animal"], "11": ["rabbit", "coop", "animal"], "10": ["rabbit", "coop", "animal"], "21": ["rabbit", "coop", "animal"], "20": ["rabbit", "coop", "animal"], "22": ["rabbit", "coop", "animal"], "23": ["rabbit", "coop", "animal"], "27": ["rabbit", "coop", "animal"], "26": ["rabbit", "coop", "animal"], "18": ["rabbit", "coop", "animal"], "24": ["rabbit", "coop", "animal"], "25": ["rabbit", "coop", "animal"], "19": ["rabbit", "coop", "animal"], "4": ["rabbit", "coop", "animal"], "5": ["rabbit", "coop", "animal"], "7": ["rabbit", "coop", "animal"], "6": ["rabbit", "coop", "animal"], "2": ["rabbit", "coop", "animal"], "3": ["rabbit", "coop", "animal"], "1": ["rabbit", "coop", "animal"], "0": ["rabbit", "coop", "animal"]}