{"8": ["character", "enemy", "monster", "metal", "head"], "9": ["character", "enemy", "monster", "metal", "head"], "14": ["character", "enemy", "monster", "metal", "head"], "15": ["character", "enemy", "monster", "metal", "head"], "17": ["character", "enemy", "monster", "bits", "metal", "head"], "16": ["character", "enemy", "monster", "bits", "metal", "head"], "12": ["character", "enemy", "monster", "metal", "head"], "13": ["character", "enemy", "monster", "metal", "head"], "11": ["character", "enemy", "monster", "metal", "head"], "10": ["character", "enemy", "monster", "metal", "head"], "18": ["character", "enemy", "monster", "bits", "metal", "head"], "19": ["character", "enemy", "monster", "bits", "metal", "head"], "4": ["character", "enemy", "monster", "metal", "head"], "5": ["character", "enemy", "monster", "metal", "head"], "7": ["character", "enemy", "monster", "metal", "head"], "6": ["character", "enemy", "monster", "metal", "head"], "2": ["character", "enemy", "monster", "metal", "head"], "3": ["character", "enemy", "monster", "metal", "head"], "1": ["character", "enemy", "monster", "metal", "head"], "0": ["character", "enemy", "monster", "metal", "head"]}