{"8": ["villager", "portrait", "character", "alex", "winter", "annoyed"], "9": ["villager", "portrait", "character", "alex", "winter", "surprised"], "10": ["villager", "portrait", "character", "alex", "winter", "annoyed"], "4": ["villager", "portrait", "character", "alex", "winter", "concerned"], "5": ["villager", "portrait", "character", "alex", "winter", "eating"], "7": ["villager", "portrait", "character", "alex", "winter"], "6": ["villager", "portrait", "character", "alex", "winter", "happy"], "2": ["villager", "portrait", "character", "alex", "winter"], "3": ["villager", "portrait", "character", "alex", "winter"], "1": ["villager", "portrait", "character", "alex", "winter", "concerned"], "0": ["villager", "portrait", "character", "alex", "winter"]}