{"8": ["character", "enemy", "monster", "crab", "rock"], "9": ["character", "enemy", "monster", "crab", "rock"], "14": ["character", "enemy", "monster", "crab", "rock"], "15": ["character", "enemy", "monster", "crab", "rock"], "17": ["character", "enemy", "monster", "crab", "rock"], "16": ["character", "enemy", "monster", "crab", "rock"], "12": ["character", "enemy", "monster", "crab", "rock"], "13": ["character", "enemy", "monster", "crab", "rock"], "11": ["character", "enemy", "monster", "crab", "rock"], "10": ["character", "enemy", "monster", "crab", "rock"], "21": ["character", "enemy", "monster", "crab", "bits", "rock"], "20": ["character", "enemy", "monster", "crab", "bits", "rock"], "22": ["character", "enemy", "monster", "crab", "bits", "rock"], "23": ["character", "enemy", "monster", "crab", "bits", "rock"], "18": ["character", "enemy", "monster", "crab", "rock"], "19": ["character", "enemy", "monster", "crab", "rock"], "4": ["character", "enemy", "monster", "crab", "rock"], "5": ["character", "enemy", "monster", "crab", "rock"], "7": ["character", "enemy", "monster", "crab", "rock"], "6": ["character", "enemy", "monster", "crab", "rock"], "2": ["character", "enemy", "monster", "crab", "rock"], "3": ["character", "enemy", "monster", "crab", "rock"], "1": ["character", "enemy", "monster", "crab", "rock"], "0": ["character", "enemy", "monster", "crab", "rock"]}