{"8": ["monster", "enemy", "character", "volcano", "partial", "magma", "sprite"], "9": ["monster", "enemy", "character", "volcano", "partial", "magma", "sprite"], "14": ["monster", "enemy", "character", "volcano", "partial", "magma", "sprite"], "29": ["monster", "enemy", "character", "volcano", "partial", "magma", "sprite"], "15": ["monster", "enemy", "character", "volcano", "partial", "magma", "sprite"], "17": ["monster", "enemy", "character", "volcano", "partial", "magma", "sprite"], "16": ["monster", "enemy", "character", "volcano", "partial", "magma", "sprite"], "12": ["monster", "enemy", "character", "volcano", "partial", "magma", "sprite"], "13": ["monster", "enemy", "character", "volcano", "partial", "magma", "sprite"], "39": ["monster", "enemy", "character", "volcano", "partial", "magma", "sprite"], "11": ["monster", "enemy", "character", "volcano", "partial", "magma", "sprite"], "10": ["monster", "enemy", "character", "volcano", "partial", "magma", "sprite"], "38": ["monster", "enemy", "character", "volcano", "magma", "sprite"], "35": ["monster", "enemy", "character", "volcano", "partial", "magma", "sprite"], "21": ["monster", "enemy", "character", "volcano", "partial", "magma", "sprite"], "20": ["monster", "enemy", "character", "volcano", "partial", "magma", "sprite"], "34": ["monster", "enemy", "character", "volcano", "magma", "sprite"], "22": ["monster", "enemy", "character", "volcano", "partial", "magma", "sprite"], "36": ["monster", "enemy", "character", "volcano", "magma", "sprite"], "37": ["monster", "enemy", "character", "volcano", "partial", "magma", "sprite"], "23": ["monster", "enemy", "character", "volcano", "partial", "magma", "sprite"], "27": ["monster", "enemy", "character", "volcano", "partial", "magma", "sprite"], "33": ["monster", "enemy", "character", "volcano", "partial", "magma", "sprite"], "32": ["monster", "enemy", "character", "volcano", "partial", "magma", "sprite"], "26": ["monster", "enemy", "character", "volcano", "partial", "magma", "sprite"], "18": ["monster", "enemy", "character", "volcano", "partial", "magma", "sprite"], "30": ["monster", "enemy", "character", "volcano", "partial", "magma", "sprite"], "24": ["monster", "enemy", "character", "volcano", "partial", "magma", "sprite"], "25": ["monster", "enemy", "character", "volcano", "partial", "magma", "sprite"], "31": ["monster", "enemy", "character", "volcano", "partial", "magma", "sprite"], "19": ["monster", "enemy", "character", "volcano", "partial", "magma", "sprite"], "4": ["monster", "enemy", "character", "volcano", "partial", "magma", "sprite"], "42": ["monster", "enemy", "character", "volcano", "magma", "sprite"], "43": ["monster", "enemy", "character", "volcano", "partial", "magma", "sprite"], "5": ["monster", "enemy", "character", "volcano", "partial", "magma", "sprite"], "41": ["monster", "enemy", "character", "volcano", "partial", "magma", "sprite"], "7": ["monster", "enemy", "character", "volcano", "partial", "magma", "sprite"], "6": ["monster", "enemy", "character", "volcano", "partial", "magma", "sprite"], "40": ["monster", "enemy", "character", "volcano", "magma", "sprite"], "44": ["monster", "enemy", "character", "volcano", "magma", "sprite"], "2": ["monster", "enemy", "character", "volcano", "partial", "magma", "sprite"], "3": ["monster", "enemy", "character", "volcano", "partial", "magma", "sprite"], "1": ["monster", "enemy", "character", "volcano", "partial", "magma", "sprite"], "0": ["monster", "enemy", "character", "volcano", "partial", "magma", "sprite"]}